sgmap/__init__.py
sgmap/_version.py
sgmap/cli.py
sgmap/core.py
sgmap-0.3.1.dist-info/METADATA
sgmap-0.3.1.dist-info/WHEEL
sgmap-0.3.1.dist-info/entry_points.txt
sgmap-0.3.1.dist-info/top_level.txt
sgmap-0.3.1.dist-info/RECORD
