Metadata-Version: 2.4
Name: sgmap
Version: 0.3.1
Summary: AWS Security Group Mapping Tool
Author: youyo
Classifier: Programming Language :: Python :: 3.12
Requires-Python: >=3.12.0
Requires-Dist: boto3>=1.20.0
Requires-Dist: click>=8.0.0
Dynamic: author
Dynamic: requires-python
